{
    "1": [
        {
            "No": "1",
            "title": "島開発方針",
            "owner": "やまたつ",
            "islandId": 1,
            "islandName": "かりん島",
            "content": "帝国の興亡は初見です。\n前回X形の島系が流行っていたようですので、それより少しだけ戦争に強い、X形とH形の混合(所謂K形？)の島開発を考えています。\nミサイル基地と防衛施設のバランス等アドバイス頂けたら嬉しいです。\n改めてよろしくお願いします。",
            "writenTurn": 3,
            "writenTime": 1728728380,
            "contentColor": "limegreen",
            "parentId": null,
            "writenCampId": "1",
            "targetCampIds": [],
            "important": false,
            "images": ["172872838011.jpg"]
        },
        {
            "No": "2",
            "title": "Re:[1]やまたつさんの発言の返信",
            "owner": "サンド",
            "islandId": 2,
            "islandName": "サンドピアリス島",
            "content": "よろです。参加経験はありまーす。\nミサ基地１０発以上、防衛は怪獣の出現や派遣等に注意して５個くらいが目安です。\nしっかり島作りをしようと思うと６０ターンだと間に合わない事が多いです。",
            "writenTurn": 3,
            "writenTime": 1715406060,
            "contentColor": "maroon",
            "parentId": "1",
            "writenCampId": "1",
            "targetCampIds": [],
            "important": false,
            "images": []
        },
        {
            "No": "3",
            "title": "Re:[2]サンドさんの発言の返信",
            "owner": "サンド",
            "islandId": 2,
            "islandName": "サンドピアリス島",
            "content": "帝国の興亡は大会毎に微妙にルールや値段が変わる事があるので経験者の方も改めてご確認ください\n一度に3ターン分更新されるのでご注意ください。多め多めに入力\n停戦期間60ターンで災害なし、10時と22時の２回更新ですのでお忘れなく\n61ターンか戦闘期間で24時間更新、150ターンに一番占有率の高い陣営の勝利\n油田枯渇6%、伐採ターン消費なし",
            "writenTurn": 3,
            "writenTime": 1715406840,
            "contentColor": "maroon",
            "parentId": "2",
            "writenCampId": "1",
            "targetCampIds": [],
            "important": false,
            "images": []
        },
        {
            "No": "4",
            "title": "Re:[2]サンドさんの発言の返信",
            "owner": "サンド",
            "islandId": 2,
            "islandName": "サンドピアリス島",
            "content": "あと方針きめて外交も早めに送らないといけないですねー\n\nGeminiと不可侵条約を結で、Copilotを攻める\nCopilotと不可侵条約を結んで、Geminiを攻める\n両陣営と不可侵条約を結んで、開発を継続\n\nみなさんどーしましょうか？",
            "writenTurn": 3,
            "writenTime": 1715408100,
            "contentColor": "maroon",
            "parentId": "3",
            "writenCampId": "1",
            "targetCampIds": [],
            "important": false,
            "images": []
        },
        {
            "No": "5",
            "title": "Re:[2]サンドさんの発言の返信",
            "owner": "やまたつ",
            "islandId": 1,
            "islandName": "かりん島",
            "content": "返信ありがとうございます 経験者の意見助かります\nステルスミサイルが謎に安いので、外交はあまり意味をなず乱戦になる予感がしますね(これ毎回の仕様じゃないのか……)\nそれでも個人的には両陣営不可侵がいいかなと思います(仮に通っても撃ち合いになると思いますが……)\n以上踏まえて60ターン目の形の良さを重視してX形寄りにしたいと思います。\n他二人の意見や所感も聞きたいです",
            "writenTurn": 6,
            "writenTime": 1715408940,
            "contentColor": "limegreen",
            "parentId": "2",
            "writenCampId": "1",
            "targetCampIds": [],
            "important": false,
            "images": []
        },
        {
            "No": "6",
            "title": "",
            "owner": "ラーメン好きの小林",
            "islandId": 3,
            "islandName": "ヤサイマシニンニクマシカラメコイ島",
            "content": "私はX型にしようかなと考えています。戦争系箱庭は久しぶりなのでおかしなところ等あったら指摘くださると幸いです。",
            "writenTurn": 6,
            "writenTime": 1715409000,
            "contentColor": "blue",
            "parentId": null,
            "writenCampId": "1",
            "targetCampIds": [],
            "important": false,
            "images": []
        },
        {
            "No": "7",
            "title": "priority",
            "owner": "ラーメン好きの小林",
            "islandId": 3,
            "islandName": "ヤサイマシニンニクマシカラメコイ島",
            "content": "私はXにしようかなと考えています。戦争系箱庭は久しぶりなのでおかしなところ等あったら指摘くださると幸いです。",
            "writenTurn": 6,
            "writenTime": 1717018400,
            "contentColor": "blue",
            "parentId": "3",
            "writenCampId": "1",
            "targetCampIds": [],
            "important": true,
            "images": []
        },
        {
            "No": "8",
            "title": "削除されました",
            "owner": "",
            "islandId": null,
            "islandName": "",
            "content": "",
            "writenTurn": null,
            "writenTime": 1745394000,
            "contentColor": "",
            "parentId": null,
            "writenCampId": "1",
            "targetCampIds": [],
            "important": false,
            "images": []
        },
        {
            "No": "9",
            "title": "削除テスト",
            "owner": "hogehoge",
            "islandId": 1,
            "islandName": "hogehoge島",
            "content": "hogehoge",
            "writenTurn": 3,
            "writenTime": 1717294000,
            "contentColor": "limegreen",
            "parentId": null,
            "writenCampId": "1",
            "targetCampIds": [],
            "important": false,
            "images": []
        },
        {
            "No": "11",
            "title": "外交文書テストログ",
            "owner": "外交官",
            "islandId": 1,
            "islandName": "Nepthune島",
            "content": "は？",
            "writenTurn": 3,
            "writenTime": 1717494000,
            "contentColor": "red",
            "parentId": null,
            "writenCampId": "2",
            "targetCampIds": ["1"],
            "important": false,
            "images": []
        },
        {
            "No": "10",
            "title": "外交文書テストログ",
            "owner": "外交官",
            "islandId": 1,
            "islandName": "hogehoge島",
            "content": "不可侵結べ",
            "writenTurn": 3,
            "writenTime": 1717394000,
            "contentColor": "aqua",
            "parentId": null,
            "writenCampId": "1",
            "targetCampIds": ["2", "3"],
            "important": false,
            "images": []
        }
    ],
    "2": [
        {
            "No": "1",
            "title": "外交文書テストログ",
            "owner": "外交官",
            "islandId": 1,
            "islandName": "hogehoge島",
            "content": "不可侵結べ",
            "writenTurn": 3,
            "writenTime": 1717394000,
            "contentColor": "aqua",
            "parentId": null,
            "writenCampId": "2",
            "targetCampIds": ["1"],
            "important": false,
            "images": []
        }
    ]
}
